solidcore/__init__.py
solidcore/__main__.py
solidcore/cli.py
solidcore-0.1.0.dist-info/LICENSE
solidcore-0.1.0.dist-info/METADATA
solidcore-0.1.0.dist-info/WHEEL
solidcore-0.1.0.dist-info/entry_points.txt
solidcore-0.1.0.dist-info/top_level.txt
solidcore-0.1.0.dist-info/RECORD
