Metadata-Version: 2.1
Name: solidcore
Version: 0.1.0
Author-email: Solid Core <solid@co.re>
Requires-Python: >=3.9
License-File: LICENSE
Requires-Dist: click
